LICENSE.txt
MANIFEST.in
README.rst
setup.cfg
setup.py
yarntf/__init__.py
yarntf/clusterspecgenerator_client.py
yarntf/clusterspecgenerator_pb2.py
yarntf/clusterspecgenerator_pb2_grpc.py
yarntf/factory.py
yarntf.egg-info/PKG-INFO
yarntf.egg-info/SOURCES.txt
yarntf.egg-info/dependency_links.txt
yarntf.egg-info/requires.txt
yarntf.egg-info/top_level.txt