Metadata-Version: 1.1
Name: yarntf
Version: 0.0.2.dev10
Summary: Easy distributed TensorFlow on Hops Hadoop
Home-page: https://github.com/hopshadoop/hops-tensorflow
Author: Tobias Johansson
Author-email: tobias@johansson.xyz
License: Apache License 2.0
Keywords: yarn tf hops hadoop tensorflow
Platform: UNKNOWN
Classifier: Development Status :: 3 - Alpha
Classifier: Intended Audience :: Developers
Classifier: Topic :: Software Development :: Libraries
Classifier: License :: OSI Approved :: Apache Software License
Classifier: Programming Language :: Python :: 2.7
